Workbook
Name Amount_Financed: AmortizationSchedule!$D$6
Name Down_Payment: AmortizationSchedule!$D$5
Name Interest_Rate: AmortizationSchedule!$D$7
Name Loan_Date: AmortizationSchedule!$D$10
Name Monthly_Payment: AmortizationSchedule!$D$9
Name Purchase_Price: AmortizationSchedule!$D$4
Name Term: AmortizationSchedule!$D$8

Sheet Challenge
B5: GoSkills Excel Challenge 51
B8: For this challenge, you'll take on these Excel missions:
B11: FALSE | C11: In the AmortizationSchedule worksheet, input the correct formula in cell D5 to compute the Down Payment.
B12: FALSE | C12: In the AmortizationSchedule worksheet, input the correct formula in cell D9 to compute the Monthly Payment.
B13: FALSE | C13: In the AmortizationSchedule worksheet, enter the appropriate formula in cell B15 to calculate the Payment Numbers.
B14: FALSE | C14: In the AmortizationSchedule worksheet, input the correct formula in cell C15 to determine the Next Payment Date.
B15: FALSE | C15: In the AmortizationSchedule worksheet, input the correct formula in cell D15 to determine Main Payment Amount.
B16: FALSE | C16: In the AmortizationSchedule worksheet, input the correct formula in cell E15 to determine the next Interest Amount.
B17: FALSE | C17: In the AmortizationSchedule worksheet, input the correct formula in cell F15 to determine the next Principal Amount.
B18: FALSE | C18: In the AmortizationSchedule worksheet, input the correct formula in cell G15 to determine the Balance Amount.
B19: FALSE | C19: In the AmortizationSchedule worksheet, input the correct formula in cell D13 to compute the Total Payment Amount.
B20: FALSE | C20: In the AmortizationSchedule worksheet, input the correct formula in cell E13 to compute the Total Interest Amount.
B21: FALSE | C21: In the AmortizationSchedule worksheet, input the correct formula in cell F13 to compute the Total Principal Amount.

Sheet AmortizationSchedule
B1: Simple Amortization Schedule
B3: Data Entry
B4: Purchase Price | D4: 555555
B5: Down Payment (25%) | D5: =Purchase_Price*0.25 -> 138888.75
B6: Amount Financed | D6: =Purchase_Price-Down_Payment -> 416666.25
B7: Annual Interest Rate | D7: 0.1
B8: Term | D8: 10
B9: Monthly Payment | D9: =PMT(Interest_Rate/12,Term*12,Amount_Financed)*(-1) -> 5506.2752
B10: Loan Date | D10: 45658
B12: Payment Numbers | C12: Date | D12: Payment | E12: Interest | F12: Principal | G12: Balance
C13: Totals: | D13: =SUM(D15:D134) -> 660753.02 | E13: =SUM(E15:E134) -> 244086.77 | F13: =SUM(F15:F134) -> 416666.25
C14: =Loan_Date -> 45658 | G14: =Amount_Financed -> 416666.25
B15: {=_xlfn.SEQUENCE((Term*12),1,1)} -> 1 | C15: =EDATE(AmortizationSchedule!C14,1) -> 45689 | D15: =Monthly_Payment -> 5506.2752 | E15: =G14*Interest_Rate/12 -> 3472.2188 | F15: =D15-E15 -> 2034.0564 | G15: =G14-F15 -> 414632.19
B16: 2 | C16: =EDATE(AmortizationSchedule!C15,1) -> 45717 | D16: =Monthly_Payment -> 5506.2752 | E16: =G15*Interest_Rate/12 -> 3455.2683 | F16: =D16-E16 -> 2051.0069 | G16: =G15-F16 -> 412581.19
B17: 3 | C17: =EDATE(AmortizationSchedule!C16,1) -> 45748 | D17: =Monthly_Payment -> 5506.2752 | E17: =G16*Interest_Rate/12 -> 3438.1766 | F17: =D17-E17 -> 2068.0986 | G17: =G16-F17 -> 410513.09
B18: 4 | C18: =EDATE(AmortizationSchedule!C17,1) -> 45778 | D18: =Monthly_Payment -> 5506.2752 | E18: =G17*Interest_Rate/12 -> 3420.9424 | F18: =D18-E18 -> 2085.3328 | G18: =G17-F18 -> 408427.76
B19: 5 | C19: =EDATE(AmortizationSchedule!C18,1) -> 45809 | D19: =Monthly_Payment -> 5506.2752 | E19: =G18*Interest_Rate/12 -> 3403.5646 | F19: =D19-E19 -> 2102.7106 | G19: =G18-F19 -> 406325.04
B20: 6 | C20: =EDATE(AmortizationSchedule!C19,1) -> 45839 | D20: =Monthly_Payment -> 5506.2752 | E20: =G19*Interest_Rate/12 -> 3386.042 | F20: =D20-E20 -> 2120.2332 | G20: =G19-F20 -> 404204.81
B21: 7 | C21: =EDATE(AmortizationSchedule!C20,1) -> 45870 | D21: =Monthly_Payment -> 5506.2752 | E21: =G20*Interest_Rate/12 -> 3368.3734 | F21: =D21-E21 -> 2137.9018 | G21: =G20-F21 -> 402066.91
B22: 8 | C22: =EDATE(AmortizationSchedule!C21,1) -> 45901 | D22: =Monthly_Payment -> 5506.2752 | E22: =G21*Interest_Rate/12 -> 3350.5576 | F22: =D22-E22 -> 2155.7176 | G22: =G21-F22 -> 399911.19
B23: 9 | C23: =EDATE(AmortizationSchedule!C22,1) -> 45931 | D23: =Monthly_Payment -> 5506.2752 | E23: =G22*Interest_Rate/12 -> 3332.5933 | F23: =D23-E23 -> 2173.6819 | G23: =G22-F23 -> 397737.51
B24: 10 | C24: =EDATE(AmortizationSchedule!C23,1) -> 45962 | D24: =Monthly_Payment -> 5506.2752 | E24: =G23*Interest_Rate/12 -> 3314.4793 | F24: =D24-E24 -> 2191.7959 | G24: =G23-F24 -> 395545.71
B25: 11 | C25: =EDATE(AmortizationSchedule!C24,1) -> 45992 | D25: =Monthly_Payment -> 5506.2752 | E25: =G24*Interest_Rate/12 -> 3296.2143 | F25: =D25-E25 -> 2210.0609 | G25: =G24-F25 -> 393335.65
B26: 12 | C26: =EDATE(AmortizationSchedule!C25,1) -> 46023 | D26: =Monthly_Payment -> 5506.2752 | E26: =G25*Interest_Rate/12 -> 3277.7971 | F26: =D26-E26 -> 2228.4781 | G26: =G25-F26 -> 391107.18
B27: 13 | C27: =EDATE(AmortizationSchedule!C26,1) -> 46054 | D27: =Monthly_Payment -> 5506.2752 | E27: =G26*Interest_Rate/12 -> 3259.2265 | F27: =D27-E27 -> 2247.0487 | G27: =G26-F27 -> 388860.13
... B134: 120 | C134: =EDATE(AmortizationSchedule!C133,1) -> 49310 | D134: =Monthly_Payment -> 5506.2752 | E134: =G133*Interest_Rate/12 -> 45.506407 | F134: =D134-E134 -> 5460.7688 | G134: =G133-F134 -> -3.6379788e-10
